{
  "project_info": {
    "project_number": "4723840473",
    "project_id": "datepick-74ce1",
    "storage_bucket": "datepick-74ce1.appspot.com"
  },
  "client": [
    {
      "client_info": {
        "mobilesdk_app_id": "1:4723840473:android:9cecc8abe321cc4a9235c8",
        "android_client_info": {
          "package_name": "app.hdj.datepick.android"
        }
      },
      "oauth_client": [
        {
          "client_id": "4723840473-r75jkuakuvb602tavrtkhqott6u5ljkb.apps.googleusercontent.com",
          "client_type": 1,
          "android_info": {
            "package_name": "app.hdj.datepick.android",
            "certificate_hash": "749305839dd5b1d1e4c4b50aa04b7b1645b0fe6d"
          }
        },
        {
          "client_id": "4723840473-dnjo7v761g4c60b1uc9s1to312v3hs6m.apps.googleusercontent.com",
          "client_type": 3
        }
      ],
      "api_key": [
        {
          "current_key": "AIzaSyDHvHDZj65t8myKnKj5j6kTGIcgz-rzT3M"
        }
      ],
      "services": {
        "appinvite_service": {
          "other_platform_oauth_client": [
            {
              "client_id": "4723840473-dnjo7v761g4c60b1uc9s1to312v3hs6m.apps.googleusercontent.com",
              "client_type": 3
            }
          ]
        }
      }
    }
  ],
  "configuration_version": "1"
}